python_tool_competition_2024/__init__.py
python_tool_competition_2024/calculation/__init__.py
python_tool_competition_2024/calculation/cli_runner.py
python_tool_competition_2024/calculation/coverage_caluclator.py
python_tool_competition_2024/calculation/generation_results_calculator.py
python_tool_competition_2024/calculation/mutation_calculator/__init__.py
python_tool_competition_2024/calculation/mutation_calculator/cosmic_ray_calculator.py
python_tool_competition_2024/calculation/mutation_calculator/helpers.py
python_tool_competition_2024/calculation/mutation_calculator/mutpy_calculator.py
python_tool_competition_2024/cli/__init__.py
python_tool_competition_2024/cli/helpers.py
python_tool_competition_2024/cli/init_command.py
python_tool_competition_2024/cli/run_command.py
python_tool_competition_2024/config.py
python_tool_competition_2024/errors.py
python_tool_competition_2024/generation_results.py
python_tool_competition_2024/generator_plugins.py
python_tool_competition_2024/generators.py
python_tool_competition_2024/py.typed
python_tool_competition_2024/reporters/__init__.py
python_tool_competition_2024/reporters/cli_reporter.py
python_tool_competition_2024/reporters/csv_reporter.py
python_tool_competition_2024/results.py
python_tool_competition_2024/target_finder.py
python_tool_competition_2024/templates/.gitignore
python_tool_competition_2024/templates/README.md
python_tool_competition_2024/templates/__var__module_name/__init__.py
python_tool_competition_2024/templates/__var__module_name/generator.py
python_tool_competition_2024/templates/targets/example1.py
python_tool_competition_2024/templates/targets/example2.py
python_tool_competition_2024/templates/targets/sub_example/__init__.py
python_tool_competition_2024/templates/targets/sub_example/example3.py
python_tool_competition_2024/templates/targets/sub_example/example4.py
python_tool_competition_2024/validation.py
python_tool_competition_2024/version.py
python_tool_competition_2024-0.2.0.dist-info/LICENSE.md
python_tool_competition_2024-0.2.0.dist-info/METADATA
python_tool_competition_2024-0.2.0.dist-info/WHEEL
python_tool_competition_2024-0.2.0.dist-info/entry_points.txt
python_tool_competition_2024-0.2.0.dist-info/RECORD
