Metadata-Version: 2.1
Name: python-tool-competition-2024
Version: 0.2.0
Summary: Pipeline to create test generators
License: GPL-3.0-or-later
Author: Nicolas Erni
Author-email: gann@zhaw.ch
Requires-Python: >=3.9,<4.0
Classifier: License :: OSI Approved :: GNU General Public License v3 or later (GPLv3+)
Classifier: Programming Language :: Python :: 3
Classifier: Programming Language :: Python :: 3.9
Classifier: Programming Language :: Python :: 3.10
Classifier: Programming Language :: Python :: 3.11
Classifier: Programming Language :: Python :: 3.12
Requires-Dist: click (>=8.1.3,<9.0.0)
Requires-Dist: cosmic-ray (>=8.3.7,<9.0.0)
Requires-Dist: defusedxml (>=0.7.1,<0.8.0)
Requires-Dist: importlib-metadata (>=6.8.0,<7.0.0) ; python_version < "3.10"
Requires-Dist: mutpy (>=0.6.1,<0.7.0)
Requires-Dist: pytest (>=7.3.2,<8.0.0)
Requires-Dist: pytest-cov (>=4.1.0,<5.0.0)
Requires-Dist: rich (>=13.4.2,<14.0.0)
Requires-Dist: toml (>=0.10.2,<0.11.0)
Requires-Dist: typing-extensions (>=4.7.1,<5.0.0)
